facexlib/__init__.py
facexlib/version.py
facexlib/alignment/__init__.py
facexlib/alignment/awing_arch.py
facexlib/alignment/convert_98_to_68_landmarks.py
facexlib/assessment/__init__.py
facexlib/assessment/hyperiqa_net.py
facexlib/detection/__init__.py
facexlib/detection/align_trans.py
facexlib/detection/matlab_cp2tform.py
facexlib/detection/retinaface.py
facexlib/detection/retinaface_net.py
facexlib/detection/retinaface_utils.py
facexlib/headpose/__init__.py
facexlib/headpose/hopenet_arch.py
facexlib/matting/__init__.py
facexlib/matting/backbone.py
facexlib/matting/mobilenetv2.py
facexlib/matting/modnet.py
facexlib/parsing/__init__.py
facexlib/parsing/bisenet.py
facexlib/parsing/parsenet.py
facexlib/parsing/resnet.py
facexlib/recognition/__init__.py
facexlib/recognition/arcface_arch.py
facexlib/tracking/__init__.py
facexlib/tracking/data_association.py
facexlib/tracking/kalman_tracker.py
facexlib/tracking/sort.py
facexlib/utils/__init__.py
facexlib/utils/face_restoration_helper.py
facexlib/utils/face_utils.py
facexlib/utils/misc.py
facexlib/visualization/__init__.py
facexlib/visualization/vis_alignment.py
facexlib/visualization/vis_detection.py
facexlib/visualization/vis_headpose.py
facexlib/weights/README.md
facexlib-0.2.5.dist-info/LICENSE
facexlib-0.2.5.dist-info/METADATA
facexlib-0.2.5.dist-info/WHEEL
facexlib-0.2.5.dist-info/top_level.txt
facexlib-0.2.5.dist-info/RECORD
