Metadata-Version: 2.1
Name: facexlib
Version: 0.2.5
Summary: Basic face library
Home-page: https://github.com/xinntao/facexlib
Author: Xintao Wang
Author-email: xintao.wang@outlook.com
License: Apache License 2.0
Keywords: computer vision,face,detection,landmark,alignment
Platform: UNKNOWN
Classifier: Development Status :: 4 - Beta
Classifier: License :: OSI Approved :: Apache Software License
Classifier: Operating System :: OS Independent
Classifier: Programming Language :: Python :: 3
Classifier: Programming Language :: Python :: 3.7
Classifier: Programming Language :: Python :: 3.8
